{"Nodes":[],"ExecutionTime":"2023-09-19T06:17:05.0591733Z","GenerationTime":"0001-01-01T00:00:00","PluginUserSpecFlowId":"d248857e-671e-47b0-9639-e8dbf0daf28e","CLIUserSpecFlowId":null,"ExecutionResults":[{"ContextType":"Scenario","FeatureFolderPath":"Features","FeatureTitle":"EnglandCustomer","ScenarioTitle":"As a resident from England estimate of how much electrical appliances cost to run","ScenarioArguments":["Electric blanket","1","30","day","34"],"Status":"OK","StepResults":[{"Duration":"00:00:07.6402726","Status":"OK","Error":null,"Outputs":null},{"Duration":"00:00:00.5039167","Status":"OK","Error":null,"Outputs":null},{"Duration":"00:00:03.2942694","Status":"OK","Error":null,"Outputs":null}],"Outputs":null},{"ContextType":"Scenario","FeatureFolderPath":"Features","FeatureTitle":"EnglandCustomer","ScenarioTitle":"As a resident from England estimate of how much electrical appliances cost to run","ScenarioArguments":["Immersion heater","40","30","week","34"],"Status":"OK","StepResults":[{"Duration":"00:00:06.6096278","Status":"OK","Error":null,"Outputs":null},{"Duration":"00:00:00.4739151","Status":"OK","Error":null,"Outputs":null},{"Duration":"00:00:03.2624026","Status":"OK","Error":null,"Outputs":null}],"Outputs":null},{"ContextType":"Scenario","FeatureFolderPath":"Features","FeatureTitle":"EnglandCustomer","ScenarioTitle":"As a resident from England estimate of how much electrical appliances cost to run","ScenarioArguments":["Broadband router","50","20","week","34"],"Status":"OK","StepResults":[{"Duration":"00:00:06.1788357","Status":"OK","Error":null,"Outputs":null},{"Duration":"00:00:00.4477445","Status":"OK","Error":null,"Outputs":null},{"Duration":"00:00:03.2589291","Status":"OK","Error":null,"Outputs":null}],"Outputs":null},{"ContextType":"Scenario","FeatureFolderPath":"Features","FeatureTitle":"EnglandCustomer","ScenarioTitle":"As a resident from England estimate of how much electrical appliances cost to run","ScenarioArguments":["Games console","1","10","day","34"],"Status":"OK","StepResults":[{"Duration":"00:00:06.1683161","Status":"OK","Error":null,"Outputs":null},{"Duration":"00:00:00.4367989","Status":"OK","Error":null,"Outputs":null},{"Duration":"00:00:03.2497521","Status":"OK","Error":null,"Outputs":null}],"Outputs":null},{"ContextType":"Scenario","FeatureFolderPath":"Features","FeatureTitle":"EnglandCustomer","ScenarioTitle":"As a resident from England estimate of how much electrical appliances cost to run","ScenarioArguments":["PC or desktop computer","40","30","week","34"],"Status":"OK","StepResults":[{"Duration":"00:00:06.8820436","Status":"OK","Error":null,"Outputs":null},{"Duration":"00:00:00.4820777","Status":"OK","Error":null,"Outputs":null},{"Duration":"00:00:03.2659239","Status":"OK","Error":null,"Outputs":null}],"Outputs":null},{"ContextType":"Scenario","FeatureFolderPath":"Features","FeatureTitle":"EnglandCustomer","ScenarioTitle":"As a resident from England estimate of how much electrical appliances cost to run","ScenarioArguments":["Dishwasher","2","20","day","34"],"Status":"OK","StepResults":[{"Duration":"00:00:07.2241227","Status":"OK","Error":null,"Outputs":null},{"Duration":"00:00:00.4294527","Status":"OK","Error":null,"Outputs":null},{"Duration":"00:00:03.2657325","Status":"OK","Error":null,"Outputs":null}],"Outputs":null},{"ContextType":"Scenario","FeatureFolderPath":"Features","FeatureTitle":"EnglandCustomer","ScenarioTitle":"As a resident from England estimate of how much electrical appliances cost to run","ScenarioArguments":["Kettle","1","44","day","34"],"Status":"OK","StepResults":[{"Duration":"00:00:06.1677145","Status":"OK","Error":null,"Outputs":null},{"Duration":"00:00:00.4360869","Status":"OK","Error":null,"Outputs":null},{"Duration":"00:00:03.2724530","Status":"OK","Error":null,"Outputs":null}],"Outputs":null},{"ContextType":"Scenario","FeatureFolderPath":"Features","FeatureTitle":"ScotlandCustomer","ScenarioTitle":"As a resident from Scotland estimate of how much electrical appliances cost to run","ScenarioArguments":["Electric blanket","1","45","day","67"],"Status":"OK","StepResults":[{"Duration":"00:00:07.1344448","Status":"OK","Error":null,"Outputs":null},{"Duration":"00:00:00.4457960","Status":"OK","Error":null,"Outputs":null},{"Duration":"00:00:03.2677868","Status":"OK","Error":null,"Outputs":null}],"Outputs":null},{"ContextType":"Scenario","FeatureFolderPath":"Features","FeatureTitle":"ScotlandCustomer","ScenarioTitle":"As a resident from Scotland estimate of how much electrical appliances cost to run","ScenarioArguments":["Fan heater","2","30","day","67"],"Status":"OK","StepResults":[{"Duration":"00:00:07.4742266","Status":"OK","Error":null,"Outputs":null},{"Duration":"00:00:00.4280016","Status":"OK","Error":null,"Outputs":null},{"Duration":"00:00:03.2760141","Status":"OK","Error":null,"Outputs":null}],"Outputs":null},{"ContextType":"Scenario","FeatureFolderPath":"Features","FeatureTitle":"ScotlandCustomer","ScenarioTitle":"As a resident from Scotland estimate of how much electrical appliances cost to run","ScenarioArguments":["Broadband router","45","20","week","67"],"Status":"OK","StepResults":[{"Duration":"00:00:06.8792270","Status":"OK","Error":null,"Outputs":null},{"Duration":"00:00:00.4707457","Status":"OK","Error":null,"Outputs":null},{"Duration":"00:00:03.2766573","Status":"OK","Error":null,"Outputs":null}],"Outputs":null},{"ContextType":"Scenario","FeatureFolderPath":"Features","FeatureTitle":"ScotlandCustomer","ScenarioTitle":"As a resident from Scotland estimate of how much electrical appliances cost to run","ScenarioArguments":["Games console","2","15","day","67"],"Status":"OK","StepResults":[{"Duration":"00:00:06.7818337","Status":"OK","Error":null,"Outputs":null},{"Duration":"00:00:00.4231457","Status":"OK","Error":null,"Outputs":null},{"Duration":"00:00:03.2687017","Status":"OK","Error":null,"Outputs":null}],"Outputs":null},{"ContextType":"Scenario","FeatureFolderPath":"Features","FeatureTitle":"ScotlandCustomer","ScenarioTitle":"As a resident from Scotland estimate of how much electrical appliances cost to run","ScenarioArguments":["PC or desktop computer","40","30","week","67"],"Status":"OK","StepResults":[{"Duration":"00:00:07.0624777","Status":"OK","Error":null,"Outputs":null},{"Duration":"00:00:00.4775066","Status":"OK","Error":null,"Outputs":null},{"Duration":"00:00:03.2773389","Status":"OK","Error":null,"Outputs":null}],"Outputs":null},{"ContextType":"Scenario","FeatureFolderPath":"Features","FeatureTitle":"ScotlandCustomer","ScenarioTitle":"As a resident from Scotland estimate of how much electrical appliances cost to run","ScenarioArguments":["Dehumidifier","30","25","week","67"],"Status":"OK","StepResults":[{"Duration":"00:00:07.0449205","Status":"OK","Error":null,"Outputs":null},{"Duration":"00:00:00.4577520","Status":"OK","Error":null,"Outputs":null},{"Duration":"00:00:03.2826594","Status":"OK","Error":null,"Outputs":null}],"Outputs":null},{"ContextType":"Scenario","FeatureFolderPath":"Features","FeatureTitle":"ScotlandCustomer","ScenarioTitle":"As a resident from Scotland estimate of how much electrical appliances cost to run","ScenarioArguments":["Dishwasher","2","25","day","67"],"Status":"OK","StepResults":[{"Duration":"00:00:06.7735287","Status":"OK","Error":null,"Outputs":null},{"Duration":"00:00:00.4230504","Status":"OK","Error":null,"Outputs":null},{"Duration":"00:00:03.2524626","Status":"OK","Error":null,"Outputs":null}],"Outputs":null},{"ContextType":"Scenario","FeatureFolderPath":"Features","FeatureTitle":"ScotlandCustomer","ScenarioTitle":"As a resident from Scotland estimate of how much electrical appliances cost to run","ScenarioArguments":["Oven","1","30","day","67"],"Status":"OK","StepResults":[{"Duration":"00:00:08.1436677","Status":"OK","Error":null,"Outputs":null},{"Duration":"00:00:00.4320825","Status":"OK","Error":null,"Outputs":null},{"Duration":"00:00:03.2718404","Status":"OK","Error":null,"Outputs":null}],"Outputs":null},{"ContextType":"Scenario","FeatureFolderPath":"Features","FeatureTitle":"ScotlandCustomer","ScenarioTitle":"As a resident from Scotland estimate of how much electrical appliances cost to run","ScenarioArguments":["Iron","2","40","day","67"],"Status":"OK","StepResults":[{"Duration":"00:00:07.7443809","Status":"OK","Error":null,"Outputs":null},{"Duration":"00:00:00.4519924","Status":"OK","Error":null,"Outputs":null},{"Duration":"00:00:03.2715280","Status":"OK","Error":null,"Outputs":null}],"Outputs":null},{"ContextType":"Scenario","FeatureFolderPath":"Features","FeatureTitle":"ScotlandCustomer","ScenarioTitle":"As a resident from Scotland estimate of how much electrical appliances cost to run","ScenarioArguments":["Vacuum cleaner","1","10","day","67"],"Status":"OK","StepResults":[{"Duration":"00:00:07.4565115","Status":"OK","Error":null,"Outputs":null},{"Duration":"00:00:00.4623223","Status":"OK","Error":null,"Outputs":null},{"Duration":"00:00:03.2620627","Status":"OK","Error":null,"Outputs":null}],"Outputs":null}],"StepReports":null}